uj/__init__.py
uj-0.1.1.dist-info/METADATA
uj-0.1.1.dist-info/WHEEL
uj-0.1.1.dist-info/licenses/LICENSE
uj-0.1.1.dist-info/RECORD
