Metadata-Version: 2.4
Name: uj
Version: 0.1.1
Summary: UI layers for ij
Project-URL: Homepage, https://github.com/i2mint/uj
Project-URL: Repository, https://github.com/i2mint/uj
License: mit
License-File: LICENSE
Requires-Python: >=3.10
Provides-Extra: dev
Requires-Dist: pytest-cov>=4.0; extra == 'dev'
Requires-Dist: pytest>=7.0; extra == 'dev'
Requires-Dist: ruff>=0.1.0; extra == 'dev'
Provides-Extra: docs
Requires-Dist: sphinx-rtd-theme>=1.0; extra == 'docs'
Requires-Dist: sphinx>=6.0; extra == 'docs'
